{
  "opportunities": [
    {
      "id": "XGD_call_14.0_21",
      "underlying_symbol": "XGD",
      "underlying_price": 35.06,
      "strategy_type": "Long Call",
      "option_type": "call",
      "strike": 14.0,
      "days_to_expiry": 21,
      "expiry_date": "2025-09-18",
      "market_price": 20.98,
      "bid": 20.88,
      "ask": 21.08,
      "volume": 0,
      "open_interest": 22319,
      "implied_volatility": 1.0,
      "delta": 1.0,
      "gamma": 0.0,
      "theta": -0.0,
      "vega": 0.0,
      "moneyness": 2.504,
      "bid_ask_spread_pct": 1.0,
      "breakeven": 34.98,
      "max_loss": 2098.0,
      "max_profit": 999999,
      "probability_of_profit": 90.0,
      "expected_value": 5455.0,
      "score": 96.5,
      "risk_reward_ratio": 3.0,
      "liquidity_score": 100.0,
      "time_decay": -0.01,
      "intrinsic_value": 21.06,
      "time_value": -0.08
    },
    {
      "id": "XGD_call_18.0_21",
      "underlying_symbol": "XGD",
      "underlying_price": 35.06,
      "strategy_type": "Long Call",
      "option_type": "call",
      "strike": 18.0,
      "days_to_expiry": 21,
      "expiry_date": "2025-09-18",
      "market_price": 17.02,
      "bid": 16.92,
      "ask": 17.12,
      "volume": 0,
      "open_interest": 17,
      "implied_volatility": 1.0,
      "delta": 1.0,
      "gamma": 0.0,
      "theta": -0.0,
      "vega": 0.0,
      "moneyness": 1.948,
      "bid_ask_spread_pct": 1.2,
      "breakeven": 35.02,
      "max_loss": 1702.0,
      "max_profit": 999999,
      "probability_of_profit": 90.0,
      "expected_value": 4425.0,
      "score": 96.5,
      "risk_reward_ratio": 3.0,
      "liquidity_score": 17.0,
      "time_decay": -0.02,
      "intrinsic_value": 17.06,
      "time_value": -0.03
    },
    {
      "id": "XGD_call_19.0_21",
      "underlying_symbol": "XGD",
      "underlying_price": 35.06,
      "strategy_type": "Long Call",
      "option_type": "call",
      "strike": 19.0,
      "days_to_expiry": 21,
      "expiry_date": "2025-09-18",
      "market_price": 16.01,
      "bid": 15.93,
      "ask": 16.09,
      "volume": 0,
      "open_interest": 12,
      "implied_volatility": 1.0,
      "delta": 1.0,
      "gamma": 0.0,
      "theta": -0.0,
      "vega": 0.0,
      "moneyness": 1.845,
      "bid_ask_spread_pct": 1.0,
      "breakeven": 35.01,
      "max_loss": 1601.0,
      "max_profit": 999999,
      "probability_of_profit": 90.0,
      "expected_value": 4163.0,
      "score": 96.5,
      "risk_reward_ratio": 3.0,
      "liquidity_score": 12.0,
      "time_decay": -0.02,
      "intrinsic_value": 16.06,
      "time_value": -0.05
    },
    {
      "id": "XGD_call_20.0_21",
      "underlying_symbol": "XGD",
      "underlying_price": 35.06,
      "strategy_type": "Long Call",
      "option_type": "call",
      "strike": 20.0,
      "days_to_expiry": 21,
      "expiry_date": "2025-09-18",
      "market_price": 15.03,
      "bid": 14.94,
      "ask": 15.12,
      "volume": 0,
      "open_interest": 34,
      "implied_volatility": 1.0,
      "delta": 1.0,
      "gamma": 0.0,
      "theta": -0.0,
      "vega": 0.0,
      "moneyness": 1.753,
      "bid_ask_spread_pct": 1.2,
      "breakeven": 35.03,
      "max_loss": 1503.0,
      "max_profit": 999999,
      "probability_of_profit": 90.0,
      "expected_value": 3908.0,
      "score": 96.5,
      "risk_reward_ratio": 3.0,
      "liquidity_score": 34.0,
      "time_decay": -0.02,
      "intrinsic_value": 15.06,
      "time_value": -0.03
    },
    {
      "id": "XGD_call_26.0_21",
      "underlying_symbol": "XGD",
      "underlying_price": 35.06,
      "strategy_type": "Long Call",
      "option_type": "call",
      "strike": 26.0,
      "days_to_expiry": 21,
      "expiry_date": "2025-09-18",
      "market_price": 9.1,
      "bid": 8.98,
      "ask": 9.21,
      "volume": 0,
      "open_interest": 6,
      "implied_volatility": 0.1,
      "delta": 1.0,
      "gamma": 0.0,
      "theta": -0.0,
      "vega": 0.0,
      "moneyness": 1.348,
      "bid_ask_spread_pct": 2.5,
      "breakeven": 35.09,
      "max_loss": 910.0,
      "max_profit": 999999,
      "probability_of_profit": 90.0,
      "expected_value": 2365.0,
      "score": 96.5,
      "risk_reward_ratio": 3.0,
      "liquidity_score": 6.0,
      "time_decay": -0.02,
      "intrinsic_value": 9.06,
      "time_value": 0.04
    },
    {
      "id": "BTCX_call_9.5_21",
      "underlying_symbol": "BTCX",
      "underlying_price": 23.26,
      "strategy_type": "Long Call",
      "option_type": "call",
      "strike": 9.5,
      "days_to_expiry": 21,
      "expiry_date": "2025-09-18",
      "market_price": 13.77,
      "bid": 13.6,
      "ask": 13.95,
      "volume": 0,
      "open_interest": 123,
      "implied_volatility": 0.1,
      "delta": 1.0,
      "gamma": 0.0,
      "theta": -0.0,
      "vega": 0.0,
      "moneyness": 2.448,
      "bid_ask_spread_pct": 2.5,
      "breakeven": 23.27,
      "max_loss": 1377.0,
      "max_profit": 999999,
      "probability_of_profit": 90.0,
      "expected_value": 3581.0,
      "score": 96.5,
      "risk_reward_ratio": 3.0,
      "liquidity_score": 100.0,
      "time_decay": -0.01,
      "intrinsic_value": 13.76,
      "time_value": 0.02
    },
    {
      "id": "EBIT_call_36.0_21",
      "underlying_symbol": "EBIT",
      "underlying_price": 55.88,
      "strategy_type": "Long Call",
      "option_type": "call",
      "strike": 36.0,
      "days_to_expiry": 21,
      "expiry_date": "2025-09-18",
      "market_price": 19.98,
      "bid": 19.7,
      "ask": 20.25,
      "volume": 0,
      "open_interest": 8,
      "implied_volatility": 67.6,
      "delta": 0.998,
      "gamma": 0.0009,
      "theta": -0.01,
      "vega": 0.0,
      "moneyness": 1.552,
      "bid_ask_spread_pct": 2.8,
      "breakeven": 55.98,
      "max_loss": 1998.0,
      "max_profit": 999999,
      "probability_of_profit": 90.0,
      "expected_value": 5194.0,
      "score": 76.1,
      "risk_reward_ratio": 3.0,
      "liquidity_score": 8.0,
      "time_decay": -0.04,
      "intrinsic_value": 19.88,
      "time_value": 0.1
    },
    {
      "id": "EBIT_call_44.25_21",
      "underlying_symbol": "EBIT",
      "underlying_price": 55.88,
      "strategy_type": "Long Call",
      "option_type": "call",
      "strike": 44.25,
      "days_to_expiry": 21,
      "expiry_date": "2025-09-18",
      "market_price": 11.93,
      "bid": 11.6,
      "ask": 12.25,
      "volume": 0,
      "open_interest": 5,
      "implied_volatility": 62.7,
      "delta": 0.95,
      "gamma": 0.0123,
      "theta": -0.03,
      "vega": 0.01,
      "moneyness": 1.263,
      "bid_ask_spread_pct": 5.5,
      "breakeven": 56.17,
      "max_loss": 1192.0,
      "max_profit": 999999,
      "probability_of_profit": 90.0,
      "expected_value": 3100.0,
      "score": 75.1,
      "risk_reward_ratio": 3.0,
      "liquidity_score": 5.0,
      "time_decay": -0.18,
      "intrinsic_value": 11.62,
      "time_value": 0.3
    },
    {
      "id": "EBIT_call_38.0_21",
      "underlying_symbol": "EBIT",
      "underlying_price": 55.88,
      "strategy_type": "Long Call",
      "option_type": "call",
      "strike": 38.0,
      "days_to_expiry": 21,
      "expiry_date": "2025-09-18",
      "market_price": 18.0,
      "bid": 17.7,
      "ask": 18.3,
      "volume": 0,
      "open_interest": 5,
      "implied_volatility": 69.9,
      "delta": 0.992,
      "gamma": 0.0024,
      "theta": -0.01,
      "vega": 0.0,
      "moneyness": 1.47,
      "bid_ask_spread_pct": 3.3,
      "breakeven": 56.0,
      "max_loss": 1800.0,
      "max_profit": 999999,
      "probability_of_profit": 90.0,
      "expected_value": 4680.0,
      "score": 75.0,
      "risk_reward_ratio": 3.0,
      "liquidity_score": 5.0,
      "time_decay": -0.07,
      "intrinsic_value": 17.88,
      "time_value": 0.12
    },
    {
      "id": "EBIT_call_44.0_21",
      "underlying_symbol": "EBIT",
      "underlying_price": 55.88,
      "strategy_type": "Long Call",
      "option_type": "call",
      "strike": 44.0,
      "days_to_expiry": 21,
      "expiry_date": "2025-09-18",
      "market_price": 12.18,
      "bid": 11.85,
      "ask": 12.5,
      "volume": 0,
      "open_interest": 5,
      "implied_volatility": 63.9,
      "delta": 0.951,
      "gamma": 0.0119,
      "theta": -0.03,
      "vega": 0.01,
      "moneyness": 1.27,
      "bid_ask_spread_pct": 5.3,
      "breakeven": 56.17,
      "max_loss": 1218.0,
      "max_profit": 999999,
      "probability_of_profit": 90.0,
      "expected_value": 3166.0,
      "score": 74.8,
      "risk_reward_ratio": 3.0,
      "liquidity_score": 5.0,
      "time_decay": -0.18,
      "intrinsic_value": 11.88,
      "time_value": 0.3
    },
    {
      "id": "EBIT_call_42.0_21",
      "underlying_symbol": "EBIT",
      "underlying_price": 55.88,
      "strategy_type": "Long Call",
      "option_type": "call",
      "strike": 42.0,
      "days_to_expiry": 21,
      "expiry_date": "2025-09-18",
      "market_price": 14.1,
      "bid": 13.8,
      "ask": 14.4,
      "volume": 0,
      "open_interest": 288,
      "implied_volatility": 67.4,
      "delta": 0.969,
      "gamma": 0.0078,
      "theta": -0.02,
      "vega": 0.01,
      "moneyness": 1.33,
      "bid_ask_spread_pct": 4.3,
      "breakeven": 56.1,
      "max_loss": 1410.0,
      "max_profit": 999999,
      "probability_of_profit": 90.0,
      "expected_value": 3666.0,
      "score": 74.7,
      "risk_reward_ratio": 3.0,
      "liquidity_score": 100.0,
      "time_decay": -0.14,
      "intrinsic_value": 13.88,
      "time_value": 0.23
    },
    {
      "id": "BTCX_call_14.0_21",
      "underlying_symbol": "BTCX",
      "underlying_price": 23.26,
      "strategy_type": "Long Call",
      "option_type": "call",
      "strike": 14.0,
      "days_to_expiry": 21,
      "expiry_date": "2025-09-18",
      "market_price": 9.3,
      "bid": 9.15,
      "ask": 9.45,
      "volume": 0,
      "open_interest": 82,
      "implied_volatility": 79.3,
      "delta": 0.997,
      "gamma": 0.0019,
      "theta": -0.0,
      "vega": 0.0,
      "moneyness": 1.661,
      "bid_ask_spread_pct": 3.2,
      "breakeven": 23.3,
      "max_loss": 930.0,
      "max_profit": 999999,
      "probability_of_profit": 90.0,
      "expected_value": 2418.0,
      "score": 72.5,
      "risk_reward_ratio": 3.0,
      "liquidity_score": 82.0,
      "time_decay": -0.02,
      "intrinsic_value": 9.26,
      "time_value": 0.04
    },
    {
      "id": "BTCX_call_20.5_49",
      "underlying_symbol": "BTCX",
      "underlying_price": 23.26,
      "strategy_type": "Long Call",
      "option_type": "call",
      "strike": 20.5,
      "days_to_expiry": 49,
      "expiry_date": "2025-10-16",
      "market_price": 3.62,
      "bid": 3.5,
      "ask": 3.75,
      "volume": 0,
      "open_interest": 10,
      "implied_volatility": 57.7,
      "delta": 0.768,
      "gamma": 0.0621,
      "theta": -0.02,
      "vega": 0.03,
      "moneyness": 1.135,
      "bid_ask_spread_pct": 6.9,
      "breakeven": 24.12,
      "max_loss": 362.0,
      "max_profit": 999999,
      "probability_of_profit": 76.8,
      "expected_value": 751.0,
      "score": 72.0,
      "risk_reward_ratio": 3.0,
      "liquidity_score": 10.0,
      "time_decay": -0.12,
      "intrinsic_value": 2.76,
      "time_value": 0.87
    },
    {
      "id": "BTCX_call_18.0_21",
      "underlying_symbol": "BTCX",
      "underlying_price": 23.26,
      "strategy_type": "Long Call",
      "option_type": "call",
      "strike": 18.0,
      "days_to_expiry": 21,
      "expiry_date": "2025-09-18",
      "market_price": 5.45,
      "bid": 5.3,
      "ask": 5.6,
      "volume": 0,
      "open_interest": 22,
      "implied_volatility": 77.9,
      "delta": 0.931,
      "gamma": 0.0307,
      "theta": -0.02,
      "vega": 0.01,
      "moneyness": 1.292,
      "bid_ask_spread_pct": 5.5,
      "breakeven": 23.45,
      "max_loss": 545.0,
      "max_profit": 999999,
      "probability_of_profit": 90.0,
      "expected_value": 1417.0,
      "score": 69.8,
      "risk_reward_ratio": 3.0,
      "liquidity_score": 22.0,
      "time_decay": -0.11,
      "intrinsic_value": 5.26,
      "time_value": 0.19
    },
    {
      "id": "BTCX_call_20.0_21",
      "underlying_symbol": "BTCX",
      "underlying_price": 23.26,
      "strategy_type": "Long Call",
      "option_type": "call",
      "strike": 20.0,
      "days_to_expiry": 21,
      "expiry_date": "2025-09-18",
      "market_price": 3.62,
      "bid": 3.5,
      "ask": 3.75,
      "volume": 2,
      "open_interest": 21,
      "implied_volatility": 67.1,
      "delta": 0.85,
      "gamma": 0.0624,
      "theta": -0.02,
      "vega": 0.01,
      "moneyness": 1.163,
      "bid_ask_spread_pct": 6.9,
      "breakeven": 23.62,
      "max_loss": 362.0,
      "max_profit": 999999,
      "probability_of_profit": 85.0,
      "expected_value": 870.0,
      "score": 69.5,
      "risk_reward_ratio": 3.0,
      "liquidity_score": 41.0,
      "time_decay": -0.16,
      "intrinsic_value": 3.26,
      "time_value": 0.37
    },
    {
      "id": "BTCC_call_19.0_21",
      "underlying_symbol": "BTCC",
      "underlying_price": 22.02,
      "strategy_type": "Long Call",
      "option_type": "call",
      "strike": 19.0,
      "days_to_expiry": 21,
      "expiry_date": "2025-09-18",
      "market_price": 3.41,
      "bid": 3.22,
      "ask": 3.6,
      "volume": 0,
      "open_interest": 221,
      "implied_volatility": 69.2,
      "delta": 0.839,
      "gamma": 0.0669,
      "theta": -0.02,
      "vega": 0.01,
      "moneyness": 1.159,
      "bid_ask_spread_pct": 11.1,
      "breakeven": 22.41,
      "max_loss": 341.0,
      "max_profit": 999999,
      "probability_of_profit": 83.9,
      "expected_value": 803.0,
      "score": 67.6,
      "risk_reward_ratio": 3.0,
      "liquidity_score": 100.0,
      "time_decay": -0.16,
      "intrinsic_value": 3.02,
      "time_value": 0.39
    },
    {
      "id": "BTCC_call_19.5_21",
      "underlying_symbol": "BTCC",
      "underlying_price": 22.02,
      "strategy_type": "Long Call",
      "option_type": "call",
      "strike": 19.5,
      "days_to_expiry": 21,
      "expiry_date": "2025-09-18",
      "market_price": 3.0,
      "bid": 2.86,
      "ask": 3.15,
      "volume": 0,
      "open_interest": 7,
      "implied_volatility": 67.8,
      "delta": 0.801,
      "gamma": 0.0779,
      "theta": -0.03,
      "vega": 0.01,
      "moneyness": 1.129,
      "bid_ask_spread_pct": 9.7,
      "breakeven": 22.5,
      "max_loss": 300.0,
      "max_profit": 999999,
      "probability_of_profit": 80.1,
      "expected_value": 663.0,
      "score": 66.8,
      "risk_reward_ratio": 3.0,
      "liquidity_score": 7.0,
      "time_decay": -0.18,
      "intrinsic_value": 2.52,
      "time_value": 0.48
    },
    {
      "id": "ETHH_call_7.25_21",
      "underlying_symbol": "ETHH",
      "underlying_price": 17.2,
      "strategy_type": "Long Call",
      "option_type": "call",
      "strike": 7.25,
      "days_to_expiry": 21,
      "expiry_date": "2025-09-18",
      "market_price": 9.98,
      "bid": 9.9,
      "ask": 10.05,
      "volume": 0,
      "open_interest": 10,
      "implied_volatility": 141.3,
      "delta": 0.997,
      "gamma": 0.0017,
      "theta": -0.0,
      "vega": 0.0,
      "moneyness": 2.372,
      "bid_ask_spread_pct": 1.5,
      "breakeven": 17.23,
      "max_loss": 998.0,
      "max_profit": 999999,
      "probability_of_profit": 90.0,
      "expected_value": 2594.0,
      "score": 66.6,
      "risk_reward_ratio": 3.0,
      "liquidity_score": 10.0,
      "time_decay": -0.02,
      "intrinsic_value": 9.95,
      "time_value": 0.03
    },
    {
      "id": "ETHH_call_7.5_21",
      "underlying_symbol": "ETHH",
      "underlying_price": 17.2,
      "strategy_type": "Long Call",
      "option_type": "call",
      "strike": 7.5,
      "days_to_expiry": 21,
      "expiry_date": "2025-09-18",
      "market_price": 9.75,
      "bid": 9.65,
      "ask": 9.86,
      "volume": 0,
      "open_interest": 10,
      "implied_volatility": 170.9,
      "delta": 0.987,
      "gamma": 0.0046,
      "theta": -0.01,
      "vega": 0.0,
      "moneyness": 2.293,
      "bid_ask_spread_pct": 2.2,
      "breakeven": 17.25,
      "max_loss": 975.0,
      "max_profit": 999999,
      "probability_of_profit": 90.0,
      "expected_value": 2536.0,
      "score": 66.1,
      "risk_reward_ratio": 3.0,
      "liquidity_score": 10.0,
      "time_decay": -0.04,
      "intrinsic_value": 9.7,
      "time_value": 0.05
    },
    {
      "id": "ETHH_call_7.75_21",
      "underlying_symbol": "ETHH",
      "underlying_price": 17.2,
      "strategy_type": "Long Call",
      "option_type": "call",
      "strike": 7.75,
      "days_to_expiry": 21,
      "expiry_date": "2025-09-18",
      "market_price": 9.51,
      "bid": 9.39,
      "ask": 9.63,
      "volume": 0,
      "open_interest": 10,
      "implied_volatility": 167.7,
      "delta": 0.986,
      "gamma": 0.0052,
      "theta": -0.01,
      "vega": 0.0,
      "moneyness": 2.219,
      "bid_ask_spread_pct": 2.5,
      "breakeven": 17.26,
      "max_loss": 951.0,
      "max_profit": 999999,
      "probability_of_profit": 90.0,
      "expected_value": 2473.0,
      "score": 65.9,
      "risk_reward_ratio": 3.0,
      "liquidity_score": 10.0,
      "time_decay": -0.05,
      "intrinsic_value": 9.45,
      "time_value": 0.06
    },
    {
      "id": "BTCC_call_20.0_21",
      "underlying_symbol": "BTCC",
      "underlying_price": 22.02,
      "strategy_type": "Long Call",
      "option_type": "call",
      "strike": 20.0,
      "days_to_expiry": 21,
      "expiry_date": "2025-09-18",
      "market_price": 2.6,
      "bid": 2.47,
      "ask": 2.73,
      "volume": 0,
      "open_interest": 211,
      "implied_volatility": 65.3,
      "delta": 0.762,
      "gamma": 0.0899,
      "theta": -0.03,
      "vega": 0.02,
      "moneyness": 1.101,
      "bid_ask_spread_pct": 10.0,
      "breakeven": 22.6,
      "max_loss": 260.0,
      "max_profit": 999999,
      "probability_of_profit": 76.2,
      "expected_value": 532.0,
      "score": 65.9,
      "risk_reward_ratio": 3.0,
      "liquidity_score": 100.0,
      "time_decay": -0.19,
      "intrinsic_value": 2.02,
      "time_value": 0.58
    },
    {
      "id": "ETHH_call_9.0_21",
      "underlying_symbol": "ETHH",
      "underlying_price": 17.2,
      "strategy_type": "Long Call",
      "option_type": "call",
      "strike": 9.0,
      "days_to_expiry": 21,
      "expiry_date": "2025-09-18",
      "market_price": 8.27,
      "bid": 8.14,
      "ask": 8.4,
      "volume": 0,
      "open_interest": 13,
      "implied_volatility": 142.9,
      "delta": 0.981,
      "gamma": 0.008,
      "theta": -0.01,
      "vega": 0.0,
      "moneyness": 1.911,
      "bid_ask_spread_pct": 3.1,
      "breakeven": 17.27,
      "max_loss": 827.0,
      "max_profit": 999999,
      "probability_of_profit": 90.0,
      "expected_value": 2150.0,
      "score": 65.6,
      "risk_reward_ratio": 3.0,
      "liquidity_score": 13.0,
      "time_decay": -0.05,
      "intrinsic_value": 8.2,
      "time_value": 0.07
    },
    {
      "id": "BTCC_call_17.0_21",
      "underlying_symbol": "BTCC",
      "underlying_price": 22.02,
      "strategy_type": "Long Call",
      "option_type": "call",
      "strike": 17.0,
      "days_to_expiry": 21,
      "expiry_date": "2025-09-18",
      "market_price": 5.29,
      "bid": 5.12,
      "ask": 5.45,
      "volume": 1,
      "open_interest": 306,
      "implied_volatility": 88.7,
      "delta": 0.909,
      "gamma": 0.0349,
      "theta": -0.02,
      "vega": 0.01,
      "moneyness": 1.296,
      "bid_ask_spread_pct": 6.2,
      "breakeven": 22.29,
      "max_loss": 528.0,
      "max_profit": 999999,
      "probability_of_profit": 90.0,
      "expected_value": 1374.0,
      "score": 65.5,
      "risk_reward_ratio": 3.0,
      "liquidity_score": 100.0,
      "time_decay": -0.14,
      "intrinsic_value": 5.02,
      "time_value": 0.26
    },
    {
      "id": "ETHH_call_9.5_21",
      "underlying_symbol": "ETHH",
      "underlying_price": 17.2,
      "strategy_type": "Long Call",
      "option_type": "call",
      "strike": 9.5,
      "days_to_expiry": 21,
      "expiry_date": "2025-09-18",
      "market_price": 7.79,
      "bid": 7.66,
      "ask": 7.92,
      "volume": 0,
      "open_interest": 16,
      "implied_volatility": 140.5,
      "delta": 0.974,
      "gamma": 0.0105,
      "theta": -0.01,
      "vega": 0.0,
      "moneyness": 1.811,
      "bid_ask_spread_pct": 3.3,
      "breakeven": 17.29,
      "max_loss": 779.0,
      "max_profit": 999999,
      "probability_of_profit": 90.0,
      "expected_value": 2025.0,
      "score": 65.3,
      "risk_reward_ratio": 3.0,
      "liquidity_score": 16.0,
      "time_decay": -0.07,
      "intrinsic_value": 7.7,
      "time_value": 0.09
    },
    {
      "id": "BTCC_call_18.0_21",
      "underlying_symbol": "BTCC",
      "underlying_price": 22.02,
      "strategy_type": "Long Call",
      "option_type": "call",
      "strike": 18.0,
      "days_to_expiry": 21,
      "expiry_date": "2025-09-18",
      "market_price": 4.39,
      "bid": 4.21,
      "ask": 4.58,
      "volume": 0,
      "open_interest": 198,
      "implied_volatility": 84.0,
      "delta": 0.868,
      "gamma": 0.0483,
      "theta": -0.02,
      "vega": 0.01,
      "moneyness": 1.224,
      "bid_ask_spread_pct": 8.4,
      "breakeven": 22.39,
      "max_loss": 439.0,
      "max_profit": 999999,
      "probability_of_profit": 86.8,
      "expected_value": 1086.0,
      "score": 64.8,
      "risk_reward_ratio": 3.0,
      "liquidity_score": 100.0,
      "time_decay": -0.17,
      "intrinsic_value": 4.02,
      "time_value": 0.37
    },
    {
      "id": "ETHX_call_9.0_21",
      "underlying_symbol": "ETHX",
      "underlying_price": 17.7,
      "strategy_type": "Long Call",
      "option_type": "call",
      "strike": 9.0,
      "days_to_expiry": 21,
      "expiry_date": "2025-09-18",
      "market_price": 9.02,
      "bid": 8.85,
      "ask": 9.2,
      "volume": 0,
      "open_interest": 53,
      "implied_volatility": 219.6,
      "delta": 0.94,
      "gamma": 0.0128,
      "theta": -0.03,
      "vega": 0.01,
      "moneyness": 1.967,
      "bid_ask_spread_pct": 3.9,
      "breakeven": 18.02,
      "max_loss": 902.0,
      "max_profit": 999999,
      "probability_of_profit": 90.0,
      "expected_value": 2346.0,
      "score": 63.8,
      "risk_reward_ratio": 3.0,
      "liquidity_score": 53.0,
      "time_decay": -0.19,
      "intrinsic_value": 8.7,
      "time_value": 0.32
    },
    {
      "id": "ETHX_call_9.5_21",
      "underlying_symbol": "ETHX",
      "underlying_price": 17.7,
      "strategy_type": "Long Call",
      "option_type": "call",
      "strike": 9.5,
      "days_to_expiry": 21,
      "expiry_date": "2025-09-18",
      "market_price": 8.52,
      "bid": 8.35,
      "ask": 8.7,
      "volume": 0,
      "open_interest": 150,
      "implied_volatility": 204.8,
      "delta": 0.936,
      "gamma": 0.0145,
      "theta": -0.03,
      "vega": 0.01,
      "moneyness": 1.863,
      "bid_ask_spread_pct": 4.1,
      "breakeven": 18.02,
      "max_loss": 852.0,
      "max_profit": 999999,
      "probability_of_profit": 90.0,
      "expected_value": 2216.0,
      "score": 63.6,
      "risk_reward_ratio": 3.0,
      "liquidity_score": 100.0,
      "time_decay": -0.19,
      "intrinsic_value": 8.2,
      "time_value": 0.32
    },
    {
      "id": "ETHX_call_10.0_21",
      "underlying_symbol": "ETHX",
      "underlying_price": 17.7,
      "strategy_type": "Long Call",
      "option_type": "call",
      "strike": 10.0,
      "days_to_expiry": 21,
      "expiry_date": "2025-09-18",
      "market_price": 8.02,
      "bid": 7.85,
      "ask": 8.2,
      "volume": 0,
      "open_interest": 19,
      "implied_volatility": 190.7,
      "delta": 0.931,
      "gamma": 0.0164,
      "theta": -0.03,
      "vega": 0.01,
      "moneyness": 1.77,
      "bid_ask_spread_pct": 4.4,
      "breakeven": 18.02,
      "max_loss": 802.0,
      "max_profit": 999999,
      "probability_of_profit": 90.0,
      "expected_value": 2086.0,
      "score": 63.4,
      "risk_reward_ratio": 3.0,
      "liquidity_score": 19.0,
      "time_decay": -0.19,
      "intrinsic_value": 7.7,
      "time_value": 0.32
    },
    {
      "id": "ETHX_call_11.0_21",
      "underlying_symbol": "ETHX",
      "underlying_price": 17.7,
      "strategy_type": "Long Call",
      "option_type": "call",
      "strike": 11.0,
      "days_to_expiry": 21,
      "expiry_date": "2025-09-18",
      "market_price": 7.08,
      "bid": 6.9,
      "ask": 7.25,
      "volume": 0,
      "open_interest": 100,
      "implied_volatility": 172.2,
      "delta": 0.914,
      "gamma": 0.0215,
      "theta": -0.03,
      "vega": 0.01,
      "moneyness": 1.609,
      "bid_ask_spread_pct": 4.9,
      "breakeven": 18.07,
      "max_loss": 708.0,
      "max_profit": 999999,
      "probability_of_profit": 90.0,
      "expected_value": 1840.0,
      "score": 62.6,
      "risk_reward_ratio": 3.0,
      "liquidity_score": 100.0,
      "time_decay": -0.2,
      "intrinsic_value": 6.7,
      "time_value": 0.38
    },
    {
      "id": "ETHX_call_11.5_21",
      "underlying_symbol": "ETHX",
      "underlying_price": 17.7,
      "strategy_type": "Long Call",
      "option_type": "call",
      "strike": 11.5,
      "days_to_expiry": 21,
      "expiry_date": "2025-09-18",
      "market_price": 6.6,
      "bid": 6.45,
      "ask": 6.75,
      "volume": 0,
      "open_interest": 20,
      "implied_volatility": 163.0,
      "delta": 0.904,
      "gamma": 0.0246,
      "theta": -0.03,
      "vega": 0.01,
      "moneyness": 1.539,
      "bid_ask_spread_pct": 4.5,
      "breakeven": 18.1,
      "max_loss": 660.0,
      "max_profit": 999999,
      "probability_of_profit": 90.0,
      "expected_value": 1716.0,
      "score": 62.3,
      "risk_reward_ratio": 3.0,
      "liquidity_score": 20.0,
      "time_decay": -0.2,
      "intrinsic_value": 6.2,
      "time_value": 0.4
    }
  ],
  "market_overview": {
    "total_opportunities": 30,
    "avg_score": 73.8,
    "avg_probability_of_profit": 88.3,
    "avg_expected_value": 2520.0,
    "total_underlyings": 10,
    "strategy_distribution": {
      "Long Call": 30
    },
    "top_scoring_opportunity": {
      "id": "XGD_call_14.0_21",
      "underlying_symbol": "XGD",
      "underlying_price": 35.06,
      "strategy_type": "Long Call",
      "option_type": "call",
      "strike": 14.0,
      "days_to_expiry": 21,
      "expiry_date": "2025-09-18",
      "market_price": 20.98,
      "bid": 20.88,
      "ask": 21.08,
      "volume": 0,
      "open_interest": 22319,
      "implied_volatility": 1.0,
      "delta": 1.0,
      "gamma": 0.0,
      "theta": -0.0,
      "vega": 0.0,
      "moneyness": 2.504,
      "bid_ask_spread_pct": 1.0,
      "breakeven": 34.98,
      "max_loss": 2098.0,
      "max_profit": 999999,
      "probability_of_profit": 90.0,
      "expected_value": 5455.0,
      "score": 96.5,
      "risk_reward_ratio": 3.0,
      "liquidity_score": 100.0,
      "time_decay": -0.01,
      "intrinsic_value": 21.06,
      "time_value": -0.08
    },
    "high_probability_count": 30,
    "positive_ev_count": 30
  },
  "underlyings": [
    {
      "symbol": "ETHX",
      "current_price": 17.7,
      "total_options": 68,
      "total_volume": 2,
      "total_open_interest": 3694,
      "avg_iv": 57.2,
      "options_expiring_soon": 0,
      "call_put_ratio": 1.62
    },
    {
      "symbol": "ETHH",
      "current_price": 17.2,
      "total_options": 67,
      "total_volume": 1,
      "total_open_interest": 2058,
      "avg_iv": 74.4,
      "options_expiring_soon": 0,
      "call_put_ratio": 2.53
    },
    {
      "symbol": "BTCC",
      "current_price": 22.02,
      "total_options": 62,
      "total_volume": 8,
      "total_open_interest": 4442,
      "avg_iv": 35.5,
      "options_expiring_soon": 2,
      "call_put_ratio": 1.82
    },
    {
      "symbol": "XIU",
      "current_price": 4.19,
      "total_options": 36,
      "total_volume": 10,
      "total_open_interest": 248001,
      "avg_iv": 18.9,
      "options_expiring_soon": 1,
      "call_put_ratio": 11.0
    },
    {
      "symbol": "EBIT",
      "current_price": 55.88,
      "total_options": 33,
      "total_volume": 2,
      "total_open_interest": 961,
      "avg_iv": 31.5,
      "options_expiring_soon": 0,
      "call_put_ratio": 1.36
    },
    {
      "symbol": "XSP",
      "current_price": 8.36,
      "total_options": 33,
      "total_volume": 3,
      "total_open_interest": 631,
      "avg_iv": 19.2,
      "options_expiring_soon": 0,
      "call_put_ratio": 15.5
    },
    {
      "symbol": "XGD",
      "current_price": 35.06,
      "total_options": 27,
      "total_volume": 2,
      "total_open_interest": 23029,
      "avg_iv": 40.5,
      "options_expiring_soon": 2,
      "call_put_ratio": 26.0
    },
    {
      "symbol": "BTCX",
      "current_price": 23.26,
      "total_options": 22,
      "total_volume": 2,
      "total_open_interest": 729,
      "avg_iv": 52.7,
      "options_expiring_soon": 0,
      "call_put_ratio": 2.67
    },
    {
      "symbol": "XFN",
      "current_price": 6.5,
      "total_options": 22,
      "total_volume": 0,
      "total_open_interest": 521,
      "avg_iv": 17.9,
      "options_expiring_soon": 0,
      "call_put_ratio": 22.0
    },
    {
      "symbol": "ZEB",
      "current_price": 4.23,
      "total_options": 20,
      "total_volume": 0,
      "total_open_interest": 84015,
      "avg_iv": 19.8,
      "options_expiring_soon": 0,
      "call_put_ratio": 5.67
    }
  ],
  "generated_at": "2025-08-28T22:34:42.174924"
}